{
  "metadata": {
    "simulation_date": "2025-09-22T22:46:40.771708",
    "initial_capital": 100000.0,
    "transaction_cost_pct": 0.001,
    "total_tickers": 8,
    "total_simulations": 32
  },
  "results_by_ticker": {
    "ABEV3.SA": {
      "model_prediction": {
        "ticker": "ABEV3.SA",
        "label": "Modelo de Predição",
        "capital_inicial": 100043.73900000002,
        "capital_final": 104329.07962791027,
        "retorno_total": 4.283467082243142
      },
      "model_simple": {
        "ticker": "ABEV3.SA",
        "label": "Simulação Simples",
        "capital_inicial": 100000.0,
        "capital_final": 104133.89048980449,
        "retorno_total": 4.1338904898044815
      },
      "buy_and_hold": {
        "ticker": "ABEV3.SA",
        "label": "Buy and Hold",
        "capital_inicial": 100000.0,
        "capital_final": 90350.64598780114,
        "retorno_total": -9.649354012198863
      }
    },
    "B3SA3.SA": {
      "model_prediction": {
        "ticker": "B3SA3.SA",
        "label": "Modelo de Predição",
        "capital_inicial": 100043.73900000002,
        "capital_final": 99477.67734995042,
        "retorno_total": -0.565814168590395
      },
      "model_simple": {
        "ticker": "B3SA3.SA",
        "label": "Simulação Simples",
        "capital_inicial": 100000.0,
        "capital_final": 94997.24790432713,
        "retorno_total": -5.002752095672869
      },
      "buy_and_hold": {
        "ticker": "B3SA3.SA",
        "label": "Buy and Hold",
        "capital_inicial": 100000.0,
        "capital_final": 74775.60944246201,
        "retorno_total": -25.22439055753799
      }
    },
    "BBAS3.SA": {
      "model_prediction": {
        "ticker": "BBAS3.SA",
        "label": "Modelo de Predição",
        "capital_inicial": 100043.73900000002,
        "capital_final": 117787.59140771689,
        "retorno_total": 17.736094817204773
      },
      "model_simple": {
        "ticker": "BBAS3.SA",
        "label": "Simulação Simples",
        "capital_inicial": 100000.0,
        "capital_final": 110347.58100929506,
        "retorno_total": 10.347581009295048
      },
      "buy_and_hold": {
        "ticker": "BBAS3.SA",
        "label": "Buy and Hold",
        "capital_inicial": 100000.0,
        "capital_final": 95679.13605531957,
        "retorno_total": -4.320863944680431
      }
    },
    "BBDC4.SA": {
      "model_prediction": {
        "ticker": "BBDC4.SA",
        "label": "Modelo de Predição",
        "capital_inicial": 100043.73900000002,
        "capital_final": 82289.04110117894,
        "retorno_total": -17.74693556667356
      },
      "model_simple": {
        "ticker": "BBDC4.SA",
        "label": "Simulação Simples",
        "capital_inicial": 100000.0,
        "capital_final": 83132.98321885559,
        "retorno_total": -16.867016781144418
      },
      "buy_and_hold": {
        "ticker": "BBDC4.SA",
        "label": "Buy and Hold",
        "capital_inicial": 100000.0,
        "capital_final": 73345.80009197087,
        "retorno_total": -26.65419990802913
      }
    },
    "ITUB4.SA": {
      "model_prediction": {
        "ticker": "ITUB4.SA",
        "label": "Modelo de Predição",
        "capital_inicial": 100043.73900000002,
        "capital_final": 107141.63255482489,
        "retorno_total": 7.094790364467363
      },
      "model_simple": {
        "ticker": "ITUB4.SA",
        "label": "Simulação Simples",
        "capital_inicial": 100000.0,
        "capital_final": 98980.4930763806,
        "retorno_total": -1.0195069236193954
      },
      "buy_and_hold": {
        "ticker": "ITUB4.SA",
        "label": "Buy and Hold",
        "capital_inicial": 100000.0,
        "capital_final": 98317.21066214197,
        "retorno_total": -1.6827893378580372
      }
    },
    "PETR4.SA": {
      "model_prediction": {
        "ticker": "PETR4.SA",
        "label": "Modelo de Predição",
        "capital_inicial": 99888.79073767576,
        "capital_final": 124114.17112252896,
        "retorno_total": 24.252351245769898
      },
      "model_simple": {
        "ticker": "PETR4.SA",
        "label": "Simulação Simples",
        "capital_inicial": 100000.0,
        "capital_final": 124062.30006101282,
        "retorno_total": 24.06230006101282
      },
      "buy_and_hold": {
        "ticker": "PETR4.SA",
        "label": "Buy and Hold",
        "capital_inicial": 100000.0,
        "capital_final": 117383.78592864318,
        "retorno_total": 17.38378592864318
      }
    },
    "VALE3.SA": {
      "model_prediction": {
        "ticker": "VALE3.SA",
        "label": "Modelo de Predição",
        "capital_inicial": 100311.11402286668,
        "capital_final": 97010.95724352045,
        "retorno_total": -3.2899213726147347
      },
      "model_simple": {
        "ticker": "VALE3.SA",
        "label": "Simulação Simples",
        "capital_inicial": 100000.0,
        "capital_final": 93057.47967483537,
        "retorno_total": -6.942520325164637
      },
      "buy_and_hold": {
        "ticker": "VALE3.SA",
        "label": "Buy and Hold",
        "capital_inicial": 100000.0,
        "capital_final": 77351.39470303607,
        "retorno_total": -22.64860529696393
      }
    },
    "VIVT3.SA": {
      "model_prediction": {
        "ticker": "VIVT3.SA",
        "label": "Modelo de Predição",
        "capital_inicial": 100043.73900000002,
        "capital_final": 99332.42037885045,
        "retorno_total": -0.7110076335207327
      },
      "model_simple": {
        "ticker": "VIVT3.SA",
        "label": "Simulação Simples",
        "capital_inicial": 100000.0,
        "capital_final": 93310.19584317086,
        "retorno_total": -6.689804156829138
      },
      "buy_and_hold": {
        "ticker": "VIVT3.SA",
        "label": "Buy and Hold",
        "capital_inicial": 100000.0,
        "capital_final": 94069.11177018369,
        "retorno_total": -5.930888229816311
      }
    }
  },
  "summary": {
    "model_performance": {
      "average_return": 3.8816280960357186,
      "best_performer": {
        "ticker": "PETR4.SA",
        "label": "Modelo de Predição",
        "capital_inicial": 99888.79073767576,
        "capital_final": 124114.17112252896,
        "retorno_total": 24.252351245769898
      },
      "worst_performer": {
        "ticker": "BBDC4.SA",
        "label": "Modelo de Predição",
        "capital_inicial": 100043.73900000002,
        "capital_final": 82289.04110117894,
        "retorno_total": -17.74693556667356
      },
      "total_return": 31.05302476828575
    },
    "buyhold_performance": {
      "average_return": -9.84091316980519,
      "best_performer": {
        "ticker": "PETR4.SA",
        "label": "Buy and Hold",
        "capital_inicial": 100000.0,
        "capital_final": 117383.78592864318,
        "retorno_total": 17.38378592864318
      },
      "worst_performer": {
        "ticker": "BBDC4.SA",
        "label": "Buy and Hold",
        "capital_inicial": 100000.0,
        "capital_final": 73345.80009197087,
        "retorno_total": -26.65419990802913
      },
      "total_return": -78.72730535844153
    },
    "simple_model_performance": {
      "average_return": 0.2527714097102366,
      "best_performer": {
        "ticker": "PETR4.SA",
        "label": "Simulação Simples",
        "capital_inicial": 100000.0,
        "capital_final": 124062.30006101282,
        "retorno_total": 24.06230006101282
      },
      "worst_performer": {
        "ticker": "BBDC4.SA",
        "label": "Simulação Simples",
        "capital_inicial": 100000.0,
        "capital_final": 83132.98321885559,
        "retorno_total": -16.867016781144418
      },
      "total_return": 2.0221712776818928
    }
  }
}