{
  "metadata": {
    "simulation_date": "2025-09-30T00:47:46.801602",
    "initial_capital": 100000.0,
    "transaction_cost_pct": 0.001,
    "total_tickers": 8,
    "total_simulations": 32
  },
  "results_by_ticker": {
    "ABEV3.SA": {
      "model_prediction": {
        "ticker": "ABEV3.SA",
        "label": "Modelo de Predição",
        "capital_inicial": 100000.0,
        "capital_final": 99446.9694114955,
        "retorno_total": -0.5530305885044995,
        "retorno_anual_pct": -0.5574424790166232,
        "sharpe_ratio": 0.006907951592179184,
        "sortino_ratio": 0.005671526358826327,
        "calmar_ratio": -0.03768198129941264,
        "max_drawdown_pct": 14.793343125652267,
        "volatilidade_pct": 11.310924686053003,
        "win_rate_pct": 49.473684210526315
      },
      "model_simple": {
        "ticker": "ABEV3.SA",
        "label": "Simulação Simples",
        "capital_inicial": 100000.0,
        "capital_final": 103025.40809064274,
        "retorno_total": 3.025408090642734,
        "retorno_anual_pct": 3.0499767707514724,
        "sharpe_ratio": 0.294967582491717,
        "sortino_ratio": 0.2697375417197942,
        "calmar_ratio": 0.18743228593581468,
        "max_drawdown_pct": 16.27241942615971,
        "volatilidade_pct": 13.131123658308145,
        "win_rate_pct": 47.368421052631575
      },
      "buy_and_hold": {
        "ticker": "ABEV3.SA",
        "label": "Buy and Hold",
        "capital_inicial": 100000.0,
        "capital_final": 90350.64598780114,
        "retorno_total": -9.649354012198863,
        "retorno_anual_pct": -9.68587277529711,
        "sharpe_ratio": -0.40074044817287446,
        "sortino_ratio": -0.541980789323025,
        "calmar_ratio": -0.49916688072336607,
        "max_drawdown_pct": 19.40407737240271,
        "volatilidade_pct": 20.355644058466158,
        "win_rate_pct": 46.0
      }
    },
    "B3SA3.SA": {
      "model_prediction": {
        "ticker": "B3SA3.SA",
        "label": "Modelo de Predição",
        "capital_inicial": 100000.0,
        "capital_final": 91327.19881687536,
        "retorno_total": -8.672801183124646,
        "retorno_anual_pct": -8.739059886449663,
        "sharpe_ratio": -0.6203508248027271,
        "sortino_ratio": -0.5508607311837022,
        "calmar_ratio": -0.5313631688744292,
        "max_drawdown_pct": 16.446491586839475,
        "volatilidade_pct": 13.363026650419037,
        "win_rate_pct": 54.6875
      },
      "model_simple": {
        "ticker": "B3SA3.SA",
        "label": "Simulação Simples",
        "capital_inicial": 100000.0,
        "capital_final": 94055.5561740563,
        "retorno_total": -5.944443825943702,
        "retorno_anual_pct": -5.9905457470524,
        "sharpe_ratio": -0.30247534655960173,
        "sortino_ratio": -0.2948227226300551,
        "calmar_ratio": -0.31071487969846945,
        "max_drawdown_pct": 19.279880490003805,
        "volatilidade_pct": 16.193498829124632,
        "win_rate_pct": 56.25
      },
      "buy_and_hold": {
        "ticker": "B3SA3.SA",
        "label": "Buy and Hold",
        "capital_inicial": 100000.0,
        "capital_final": 74775.60944246201,
        "retorno_total": -25.22439055753799,
        "retorno_anual_pct": -25.310936676535988,
        "sharpe_ratio": -0.9181851192869608,
        "sortino_ratio": -1.4632680358875503,
        "calmar_ratio": -0.7398142204969136,
        "max_drawdown_pct": 34.21255766013162,
        "volatilidade_pct": 27.71794463219498,
        "win_rate_pct": 49.2
      }
    },
    "BBAS3.SA": {
      "model_prediction": {
        "ticker": "BBAS3.SA",
        "label": "Modelo de Predição",
        "capital_inicial": 100000.0,
        "capital_final": 100000.0,
        "retorno_total": 0.0,
        "retorno_anual_pct": 0.0,
        "sharpe_ratio": -Infinity,
        "sortino_ratio": 0,
        "calmar_ratio": 0,
        "max_drawdown_pct": 0.0,
        "volatilidade_pct": 0.0,
        "win_rate_pct": 0.0
      },
      "model_simple": {
        "ticker": "BBAS3.SA",
        "label": "Simulação Simples",
        "capital_inicial": 100000.0,
        "capital_final": 100000.0,
        "retorno_total": 0.0,
        "retorno_anual_pct": 0.0,
        "sharpe_ratio": -Infinity,
        "sortino_ratio": 0,
        "calmar_ratio": 0,
        "max_drawdown_pct": 0.0,
        "volatilidade_pct": 0.0,
        "win_rate_pct": 0.0
      },
      "buy_and_hold": {
        "ticker": "BBAS3.SA",
        "label": "Buy and Hold",
        "capital_inicial": 100000.0,
        "capital_final": 95679.13605531957,
        "retorno_total": -4.320863944680431,
        "retorno_anual_pct": -4.337699675634998,
        "sharpe_ratio": -0.17594236199285773,
        "sortino_ratio": -0.25411692712941314,
        "calmar_ratio": -0.2684132960179686,
        "max_drawdown_pct": 16.160524608827934,
        "volatilidade_pct": 17.04757031834731,
        "win_rate_pct": 52.800000000000004
      }
    },
    "BBDC4.SA": {
      "model_prediction": {
        "ticker": "BBDC4.SA",
        "label": "Modelo de Predição",
        "capital_inicial": 100000.0,
        "capital_final": 90071.09354960649,
        "retorno_total": -9.928906450393505,
        "retorno_anual_pct": -10.00422546321833,
        "sharpe_ratio": -0.33398536339632556,
        "sortino_ratio": -0.2744865427836129,
        "calmar_ratio": -0.37409825237114297,
        "max_drawdown_pct": 26.742240573989996,
        "volatilidade_pct": 23.313529464808042,
        "win_rate_pct": 48.29931972789115
      },
      "model_simple": {
        "ticker": "BBDC4.SA",
        "label": "Simulação Simples",
        "capital_inicial": 100000.0,
        "capital_final": 89781.69651121026,
        "retorno_total": -10.218303488789736,
        "retorno_anual_pct": -10.295689993182645,
        "sharpe_ratio": -0.311438678245464,
        "sortino_ratio": -0.24903386038829392,
        "calmar_ratio": -0.3652393233822718,
        "max_drawdown_pct": 28.188886940869807,
        "volatilidade_pct": 24.790601758970976,
        "win_rate_pct": 48.29931972789115
      },
      "buy_and_hold": {
        "ticker": "BBDC4.SA",
        "label": "Buy and Hold",
        "capital_inicial": 100000.0,
        "capital_final": 73345.80009197087,
        "retorno_total": -26.65419990802913,
        "retorno_anual_pct": -26.744726042664023,
        "sharpe_ratio": -1.0044334133942063,
        "sortino_ratio": -1.098557853322212,
        "calmar_ratio": -0.9640607906177172,
        "max_drawdown_pct": 27.7417423288499,
        "volatilidade_pct": 27.268443406948716,
        "win_rate_pct": 46.800000000000004
      }
    },
    "ITUB4.SA": {
      "model_prediction": {
        "ticker": "ITUB4.SA",
        "label": "Modelo de Predição",
        "capital_inicial": 100000.0,
        "capital_final": 100000.0,
        "retorno_total": 0.0,
        "retorno_anual_pct": 0.0,
        "sharpe_ratio": -Infinity,
        "sortino_ratio": 0,
        "calmar_ratio": 0,
        "max_drawdown_pct": 0.0,
        "volatilidade_pct": 0.0,
        "win_rate_pct": 0.0
      },
      "model_simple": {
        "ticker": "ITUB4.SA",
        "label": "Simulação Simples",
        "capital_inicial": 100000.0,
        "capital_final": 100000.0,
        "retorno_total": 0.0,
        "retorno_anual_pct": 0.0,
        "sharpe_ratio": -Infinity,
        "sortino_ratio": 0,
        "calmar_ratio": 0,
        "max_drawdown_pct": 0.0,
        "volatilidade_pct": 0.0,
        "win_rate_pct": 0.0
      },
      "buy_and_hold": {
        "ticker": "ITUB4.SA",
        "label": "Buy and Hold",
        "capital_inicial": 100000.0,
        "capital_final": 98317.21066214197,
        "retorno_total": -1.6827893378580372,
        "retorno_anual_pct": -1.6894367240500197,
        "sharpe_ratio": -0.0015325068342512116,
        "sortino_ratio": -0.002384137613784716,
        "calmar_ratio": -0.1025314033304946,
        "max_drawdown_pct": 16.477261299198002,
        "volatilidade_pct": 18.38064268833971,
        "win_rate_pct": 48.4
      }
    },
    "PETR4.SA": {
      "model_prediction": {
        "ticker": "PETR4.SA",
        "label": "Modelo de Predição",
        "capital_inicial": 100000.0,
        "capital_final": 122464.71056192505,
        "retorno_total": 22.46471056192505,
        "retorno_anual_pct": 22.6634140485491,
        "sharpe_ratio": 1.0485187299442775,
        "sortino_ratio": 1.5362218617912695,
        "calmar_ratio": 1.415887128056368,
        "max_drawdown_pct": 16.006511818254797,
        "volatilidade_pct": 21.82710152788762,
        "win_rate_pct": 50.0
      },
      "model_simple": {
        "ticker": "PETR4.SA",
        "label": "Simulação Simples",
        "capital_inicial": 100000.0,
        "capital_final": 123337.85177839482,
        "retorno_total": 23.337851778394825,
        "retorno_anual_pct": 23.544993513985514,
        "sharpe_ratio": 1.0723845505510683,
        "sortino_ratio": 1.5860613978098799,
        "calmar_ratio": 1.5469116585839378,
        "max_drawdown_pct": 15.220645201897886,
        "volatilidade_pct": 22.05928618843707,
        "win_rate_pct": 50.43859649122807
      },
      "buy_and_hold": {
        "ticker": "PETR4.SA",
        "label": "Buy and Hold",
        "capital_inicial": 100000.0,
        "capital_final": 117383.78592864318,
        "retorno_total": 17.38378592864318,
        "retorno_anual_pct": 17.45876647598339,
        "sharpe_ratio": 0.7714891618226246,
        "sortino_ratio": 1.0213926291829294,
        "calmar_ratio": 1.0330775205938558,
        "max_drawdown_pct": 16.89976417834294,
        "volatilidade_pct": 25.016569680101536,
        "win_rate_pct": 50.0
      }
    },
    "VALE3.SA": {
      "model_prediction": {
        "ticker": "VALE3.SA",
        "label": "Modelo de Predição",
        "capital_inicial": 100000.0,
        "capital_final": 88216.5602186004,
        "retorno_total": -11.783439781399608,
        "retorno_anual_pct": -11.871876973344387,
        "sharpe_ratio": -1.03527459270539,
        "sortino_ratio": -0.6649502756017831,
        "calmar_ratio": -0.6996065020106677,
        "max_drawdown_pct": 16.9693634053209,
        "volatilidade_pct": 11.606348312116312,
        "win_rate_pct": 40.0
      },
      "model_simple": {
        "ticker": "VALE3.SA",
        "label": "Simulação Simples",
        "capital_inicial": 100000.0,
        "capital_final": 88821.21957297562,
        "retorno_total": -11.178780427024382,
        "retorno_anual_pct": -11.262974708992346,
        "sharpe_ratio": -0.9374669166011459,
        "sortino_ratio": -0.6025635307885395,
        "calmar_ratio": -0.652493059577665,
        "max_drawdown_pct": 17.261447526020365,
        "volatilidade_pct": 12.027295578678155,
        "win_rate_pct": 40.0
      },
      "buy_and_hold": {
        "ticker": "VALE3.SA",
        "label": "Buy and Hold",
        "capital_inicial": 100000.0,
        "capital_final": 77351.39470303607,
        "retorno_total": -22.64860529696393,
        "retorno_anual_pct": -22.72770718886147,
        "sharpe_ratio": -1.006382247033826,
        "sortino_ratio": -1.7904369972563687,
        "calmar_ratio": -0.9567695593171174,
        "max_drawdown_pct": 23.75463032611854,
        "volatilidade_pct": 23.0884031254387,
        "win_rate_pct": 40.400000000000006
      }
    },
    "VIVT3.SA": {
      "model_prediction": {
        "ticker": "VIVT3.SA",
        "label": "Modelo de Predição",
        "capital_inicial": 100000.0,
        "capital_final": 102544.14305655356,
        "retorno_total": 2.5441430565535494,
        "retorno_anual_pct": 2.5647550107038786,
        "sharpe_ratio": 0.7340621335609455,
        "sortino_ratio": 0.4036954672991431,
        "calmar_ratio": 1.6884125216294743,
        "max_drawdown_pct": 1.5190333984426108,
        "volatilidade_pct": 3.5491934463815205,
        "win_rate_pct": 53.84615384615385
      },
      "model_simple": {
        "ticker": "VIVT3.SA",
        "label": "Simulação Simples",
        "capital_inicial": 100000.0,
        "capital_final": 102722.19649026352,
        "retorno_total": 2.7221964902635287,
        "retorno_anual_pct": 2.7442701940384673,
        "sharpe_ratio": 0.576579709697558,
        "sortino_ratio": 0.2660931120872006,
        "calmar_ratio": 0.8168262618102529,
        "max_drawdown_pct": 3.3596742934741193,
        "volatilidade_pct": 4.924125872397779,
        "win_rate_pct": 57.692307692307686
      },
      "buy_and_hold": {
        "ticker": "VIVT3.SA",
        "label": "Buy and Hold",
        "capital_inicial": 100000.0,
        "capital_final": 94069.11177018369,
        "retorno_total": -5.930888229816311,
        "retorno_anual_pct": -5.953799491437328,
        "sharpe_ratio": -0.15813278750606483,
        "sortino_ratio": -0.2299356338405818,
        "calmar_ratio": -0.2799112045204126,
        "max_drawdown_pct": 21.270314997351758,
        "volatilidade_pct": 22.709159146712526,
        "win_rate_pct": 48.8
      }
    }
  },
  "summary": {
    "model_performance": {
      "average_return": -0.7411655481179575,
      "best_performer": {
        "ticker": "PETR4.SA",
        "label": "Modelo de Predição",
        "capital_inicial": 100000.0,
        "capital_final": 122464.71056192505,
        "retorno_total": 22.46471056192505,
        "retorno_anual_pct": 22.6634140485491,
        "sharpe_ratio": 1.0485187299442775,
        "sortino_ratio": 1.5362218617912695,
        "calmar_ratio": 1.415887128056368,
        "max_drawdown_pct": 16.006511818254797,
        "volatilidade_pct": 21.82710152788762,
        "win_rate_pct": 50.0
      },
      "worst_performer": {
        "ticker": "VALE3.SA",
        "label": "Modelo de Predição",
        "capital_inicial": 100000.0,
        "capital_final": 88216.5602186004,
        "retorno_total": -11.783439781399608,
        "retorno_anual_pct": -11.871876973344387,
        "sharpe_ratio": -1.03527459270539,
        "sortino_ratio": -0.6649502756017831,
        "calmar_ratio": -0.6996065020106677,
        "max_drawdown_pct": 16.9693634053209,
        "volatilidade_pct": 11.606348312116312,
        "win_rate_pct": 40.0
      },
      "total_return": -5.92932438494366
    },
    "buyhold_performance": {
      "average_return": -9.84091316980519,
      "best_performer": {
        "ticker": "PETR4.SA",
        "label": "Buy and Hold",
        "capital_inicial": 100000.0,
        "capital_final": 117383.78592864318,
        "retorno_total": 17.38378592864318,
        "retorno_anual_pct": 17.45876647598339,
        "sharpe_ratio": 0.7714891618226246,
        "sortino_ratio": 1.0213926291829294,
        "calmar_ratio": 1.0330775205938558,
        "max_drawdown_pct": 16.89976417834294,
        "volatilidade_pct": 25.016569680101536,
        "win_rate_pct": 50.0
      },
      "worst_performer": {
        "ticker": "BBDC4.SA",
        "label": "Buy and Hold",
        "capital_inicial": 100000.0,
        "capital_final": 73345.80009197087,
        "retorno_total": -26.65419990802913,
        "retorno_anual_pct": -26.744726042664023,
        "sharpe_ratio": -1.0044334133942063,
        "sortino_ratio": -1.098557853322212,
        "calmar_ratio": -0.9640607906177172,
        "max_drawdown_pct": 27.7417423288499,
        "volatilidade_pct": 27.268443406948716,
        "win_rate_pct": 46.800000000000004
      },
      "total_return": -78.72730535844153
    },
    "simple_model_performance": {
      "average_return": 0.21799107719290844,
      "best_performer": {
        "ticker": "PETR4.SA",
        "label": "Simulação Simples",
        "capital_inicial": 100000.0,
        "capital_final": 123337.85177839482,
        "retorno_total": 23.337851778394825,
        "retorno_anual_pct": 23.544993513985514,
        "sharpe_ratio": 1.0723845505510683,
        "sortino_ratio": 1.5860613978098799,
        "calmar_ratio": 1.5469116585839378,
        "max_drawdown_pct": 15.220645201897886,
        "volatilidade_pct": 22.05928618843707,
        "win_rate_pct": 50.43859649122807
      },
      "worst_performer": {
        "ticker": "VALE3.SA",
        "label": "Simulação Simples",
        "capital_inicial": 100000.0,
        "capital_final": 88821.21957297562,
        "retorno_total": -11.178780427024382,
        "retorno_anual_pct": -11.262974708992346,
        "sharpe_ratio": -0.9374669166011459,
        "sortino_ratio": -0.6025635307885395,
        "calmar_ratio": -0.652493059577665,
        "max_drawdown_pct": 17.261447526020365,
        "volatilidade_pct": 12.027295578678155,
        "win_rate_pct": 40.0
      },
      "total_return": 1.7439286175432676
    }
  }
}